search/__init__.py
search/views.py
wagtail_all_in_one_accessibility/__init__.py
wagtail_all_in_one_accessibility/admin.py
wagtail_all_in_one_accessibility/apps.py
wagtail_all_in_one_accessibility/context_processors.py
wagtail_all_in_one_accessibility/models.py
wagtail_all_in_one_accessibility/panels.py
wagtail_all_in_one_accessibility/tests.py
wagtail_all_in_one_accessibility/urls.py
wagtail_all_in_one_accessibility/views.py
wagtail_all_in_one_accessibility/wagtail_hooks.py
wagtail_all_in_one_accessibility/widgets.py
wagtail_all_in_one_accessibility/migrations/0001_initial.py
wagtail_all_in_one_accessibility/migrations/0002_allinoneaccessibility_aioa_color_code_and_more.py
wagtail_all_in_one_accessibility/migrations/0003_delete_customaccessibilitysettings_and_more.py
wagtail_all_in_one_accessibility/migrations/0004_allinoneaccessibility_domain_url.py
wagtail_all_in_one_accessibility/migrations/0005_alter_allinoneaccessibility_to_the_bottom_and_more.py
wagtail_all_in_one_accessibility/migrations/0006_alter_allinoneaccessibility_options.py
wagtail_all_in_one_accessibility/migrations/__init__.py
wagtail_all_in_one_accessibility/static/css/admin.css
wagtail_all_in_one_accessibility/static/css/index.css
wagtail_all_in_one_accessibility/static/js/conditional_fields.js
wagtail_all_in_one_accessibility/static/js/fill_domain_url.js
wagtail_all_in_one_accessibility/templates/home.html
wagtail_all_in_one_accessibility/templates/widgets/dependent_radio.html
wagtail_all_in_one_accessibility/templates/widgets/icon_type_radio.html
wagtail_package/__init__.py
wagtail_package/urls.py
wagtail_package/wsgi.py
wagtail_package/settings/__init__.py
wagtail_package/settings/base.py
wagtail_package/settings/dev.py
wagtail_package/settings/production.py
wagtail_all_in_one_accessibility-2.0.dist-info/METADATA
wagtail_all_in_one_accessibility-2.0.dist-info/WHEEL
wagtail_all_in_one_accessibility-2.0.dist-info/top_level.txt
wagtail_all_in_one_accessibility-2.0.dist-info/RECORD
